README.md
setup.py
tfvarman/cli.py
tfvarman.egg-info/PKG-INFO
tfvarman.egg-info/SOURCES.txt
tfvarman.egg-info/dependency_links.txt
tfvarman.egg-info/entry_points.txt
tfvarman.egg-info/requires.txt
tfvarman.egg-info/top_level.txt
tfvarman/utils/__init__.py
tfvarman/utils/api.py
tfvarman/utils/varfile.py