Metadata-Version: 2.1
Name: tfvarman
Version: 0.0.0.post4
Summary: variable management cli tool for terraform cloud
Home-page: https://github.com/dsikes/tfvarman
Author: Dan Sikes
Author-email: dansikes7@gmail.com
License: UNKNOWN
Project-URL: Source, https://github.com/dsikes/tfvarman
Keywords: terraform,automation,tfvars,terraform variables
Platform: UNKNOWN
